txt2musicxml/__init__.py
txt2musicxml/concrete_chords_visitor.py
txt2musicxml/concrete_front_matter_visitor.py
txt2musicxml/constants.py
txt2musicxml/empty_template.xml
txt2musicxml/enums.py
txt2musicxml/grammer/.antlr/Chords.interp
txt2musicxml/grammer/.antlr/Chords.tokens
txt2musicxml/grammer/.antlr/ChordsBaseListener.class
txt2musicxml/grammer/.antlr/ChordsBaseListener.java
txt2musicxml/grammer/.antlr/ChordsLexer.class
txt2musicxml/grammer/.antlr/ChordsLexer.interp
txt2musicxml/grammer/.antlr/ChordsLexer.java
txt2musicxml/grammer/.antlr/ChordsLexer.tokens
txt2musicxml/grammer/.antlr/ChordsListener.class
txt2musicxml/grammer/.antlr/ChordsListener.java
txt2musicxml/grammer/.antlr/ChordsParser$AlterationContext.class
txt2musicxml/grammer/.antlr/ChordsParser$BarContext.class
txt2musicxml/grammer/.antlr/ChordsParser$BassContext.class
txt2musicxml/grammer/.antlr/ChordsParser$ChordContext.class
txt2musicxml/grammer/.antlr/ChordsParser$Chord_or_slashContext.class
txt2musicxml/grammer/.antlr/ChordsParser$Front_matterContext.class
txt2musicxml/grammer/.antlr/ChordsParser$Left_barlinesContext.class
txt2musicxml/grammer/.antlr/ChordsParser$LineContext.class
txt2musicxml/grammer/.antlr/ChordsParser$NoteContext.class
txt2musicxml/grammer/.antlr/ChordsParser$Right_barlinesContext.class
txt2musicxml/grammer/.antlr/ChordsParser$RootContext.class
txt2musicxml/grammer/.antlr/ChordsParser$SheetContext.class
txt2musicxml/grammer/.antlr/ChordsParser$SimileContext.class
txt2musicxml/grammer/.antlr/ChordsParser$SlashContext.class
txt2musicxml/grammer/.antlr/ChordsParser$SuffixContext.class
txt2musicxml/grammer/.antlr/ChordsParser$Time_signatureContext.class
txt2musicxml/grammer/.antlr/ChordsParser$Title_authorContext.class
txt2musicxml/grammer/.antlr/ChordsParser.class
txt2musicxml/grammer/.antlr/ChordsParser.java
txt2musicxml/grammer/.antlr/FrontMatter.interp
txt2musicxml/grammer/.antlr/FrontMatter.tokens
txt2musicxml/grammer/.antlr/FrontMatterLexer.class
txt2musicxml-0.1.12.dist-info/METADATA
txt2musicxml-0.1.12.dist-info/WHEEL
txt2musicxml-0.1.12.dist-info/entry_points.txt
txt2musicxml-0.1.12.dist-info/RECORD
