Metadata-Version: 2.1
Name: txt2musicxml
Version: 0.1.12
Summary: CLI tool to convert chords written in simple text to musicxml files that can be used with a music notation software
Home-page: https://github.com/noamtamir/txt2musicxml
License: MIT
Keywords: musicxml,music,xml,chords
Author: noamtamir
Author-email: noam.tamir@gmail.com
Requires-Python: >=3.9,<4.0
Classifier: License :: OSI Approved :: MIT License
Classifier: Programming Language :: Python :: 3
Classifier: Programming Language :: Python :: 3.9
Classifier: Programming Language :: Python :: 3.10
Classifier: Programming Language :: Python :: 3.11
Classifier: Programming Language :: Python :: 3.12
Classifier: Programming Language :: Python :: 3.13
Requires-Dist: antlr4-python3-runtime (>=4.13.2,<5.0.0)
Project-URL: Repository, https://github.com/noamtamir/txt2musicxml
